promptguard_pro/__init__.py
promptguard_pro/caching/__init__.py
promptguard_pro/caching/base.py
promptguard_pro/caching/disk.py
promptguard_pro/caching/memory.py
promptguard_pro/caching/redis.py
promptguard_pro/core/__init__.py
promptguard_pro/core/chain.py
promptguard_pro/core/executor.py
promptguard_pro/core/models.py
promptguard_pro/core/response.py
promptguard_pro/exceptions.py
promptguard_pro/observability/__init__.py
promptguard_pro/providers/__init__.py
promptguard_pro/providers/anthropic_provider.py
promptguard_pro/providers/base.py
promptguard_pro/providers/cohere_provider.py
promptguard_pro/providers/google_provider.py
promptguard_pro/providers/groq_provider.py
promptguard_pro/providers/openai_provider.py
promptguard_pro/retry/__init__.py
promptguard_pro/retry/strategies.py
promptguard_pro/utils/__init__.py
promptguard_pro/validation/__init__.py
promptguard_pro/validation/schema.py
promptguard_pro/validation/semantic.py
promptguard_pro-0.1.3.dist-info/METADATA
promptguard_pro-0.1.3.dist-info/WHEEL
promptguard_pro-0.1.3.dist-info/licenses/LICENSE
promptguard_pro-0.1.3.dist-info/RECORD
