Metadata-Version: 2.4
Name: promptguard-pro
Version: 0.1.3
Summary: Production-ready framework for reliable LLM orchestration
License: MIT
License-File: LICENSE
Keywords: llm,ai,prompt,reliability,orchestration
Author: PromptGuard Team
Author-email: team@promptguard.dev
Requires-Python: >=3.9,<4.0
Classifier: Development Status :: 4 - Beta
Classifier: Intended Audience :: Developers
Classifier: License :: OSI Approved :: MIT License
Classifier: Programming Language :: Python :: 3
Classifier: Programming Language :: Python :: 3.9
Classifier: Programming Language :: Python :: 3.10
Classifier: Programming Language :: Python :: 3.11
Classifier: Programming Language :: Python :: 3.12
Classifier: Programming Language :: Python :: 3.13
Classifier: Programming Language :: Python :: 3.14
Provides-Extra: all
Provides-Extra: cache
Provides-Extra: metrics
Provides-Extra: providers
Provides-Extra: validation
Requires-Dist: aiohttp (>=3.9.0,<4.0.0)
Requires-Dist: anthropic (>=0.21.0,<0.22.0)
Requires-Dist: cohere (>=5.0.0,<6.0.0) ; extra == "providers" or extra == "all"
Requires-Dist: google-generativeai (>=0.3.0,<0.4.0) ; extra == "providers" or extra == "all"
Requires-Dist: groq (>=0.9.0,<0.10.0) ; extra == "providers" or extra == "all"
Requires-Dist: openai (>=1.12.0,<2.0.0)
Requires-Dist: prometheus-client (>=0.19.0,<0.20.0) ; extra == "metrics" or extra == "all"
Requires-Dist: pydantic (>=2.5.0,<3.0.0)
Requires-Dist: pydantic-settings (>=2.0.0,<3.0.0)
Requires-Dist: redis (>=5.0.0,<6.0.0) ; extra == "cache" or extra == "all"
Requires-Dist: sentence-transformers (>=2.3.0,<3.0.0) ; extra == "validation" or extra == "all"
Requires-Dist: structlog (>=24.1.0,<25.0.0)
Requires-Dist: tiktoken (>=0.6.0,<0.7.0)
Project-URL: Documentation, https://promptguard.dev/docs
Project-URL: Homepage, https://promptguard.dev
Project-URL: Repository, https://github.com/promptguard/promptguard
